sais/__init__.py
sais/benchmarks.py
sais/symbiotic_ais.py
sais-0.3.7.dist-info/licenses/LICENSE
sais-0.3.7.dist-info/METADATA
sais-0.3.7.dist-info/WHEEL
sais-0.3.7.dist-info/top_level.txt
sais-0.3.7.dist-info/RECORD
