Metadata-Version: 2.4
Name: sais
Version: 0.3.7
Summary: Symbiotic Artificial Immune Systems
Home-page: https://github.com/Rqcker/SymbioticAIS
Author: Junhao
Author-email: junhao.song23@imperial.ac.uk
License-File: LICENSE
Requires-Dist: numpy>=1.23.5
Dynamic: author
Dynamic: author-email
Dynamic: description
Dynamic: description-content-type
Dynamic: home-page
Dynamic: license-file
Dynamic: requires-dist
Dynamic: summary
